aimini/__init__.py
aimini/_modidx.py
aimini/accel.py
aimini/activations.py
aimini/augment.py
aimini/conv.py
aimini/datasets.py
aimini/fid.py
aimini/init.py
aimini/learner.py
aimini/lsh.py
aimini/resnet.py
aimini/sgd.py
aimini/training.py
aimini-0.0.4.dist-info/METADATA
aimini-0.0.4.dist-info/WHEEL
aimini-0.0.4.dist-info/entry_points.txt
aimini-0.0.4.dist-info/top_level.txt
aimini-0.0.4.dist-info/RECORD
